MANIFEST.in
README.md
setup.cfg
setup.py
example/__init__.py
example/app1.py
example/app2.py
example/keyard_app.py
keyard/__init__.py
keyard/api.py
keyard/commands.py
keyard/helpers.py
keyard/load_balancer.py
keyard/query.py
keyard/store.py
keyard.egg-info/PKG-INFO
keyard.egg-info/SOURCES.txt
keyard.egg-info/dependency_links.txt
keyard.egg-info/requires.txt
keyard.egg-info/top_level.txt
keyard/app/__init__.py
keyard/app/errors.py
keyard/app/middlewares.py
keyard/app/resource.py
keyard/app/utils.py
keyard/testutils/__init__.py
tests/app/__init__.py
tests/app/test_app.py
tests/app/test_integration_app.py
tests/app/test_utils.py