Metadata-Version: 1.0
Name: keyard
Version: 0.1.1
Summary: Simple Service Registry
Home-page: https://github.com/rzanluchi/keyard
Author: Raphael Bernardi Zanluchi
Author-email: raphael.zanluchi@gmail.com
License: MIT
Download-URL: https://github.com/rzanluchi/keyard/tarball/0.1.1
Keywords: service registry
Platform: UNKNOWN
Classifier: Development Status :: 4 - Beta
Classifier: Intended Audience :: Developers
Classifier: Topic :: Software Development :: Build Tools
Classifier: License :: OSI Approved :: MIT License
Classifier: Programming Language :: Python :: 2
Classifier: Programming Language :: Python :: 2.6
Classifier: Programming Language :: Python :: 2.7
